tomlq/__init__.py
tomlq-0.1.0.dist-info/AUTHORS.md
tomlq-0.1.0.dist-info/LICENSE
tomlq-0.1.0.dist-info/METADATA
tomlq-0.1.0.dist-info/WHEEL
tomlq-0.1.0.dist-info/entry_points.txt
tomlq-0.1.0.dist-info/top_level.txt
tomlq-0.1.0.dist-info/RECORD
