Metadata-Version: 2.1
Name: tomlq
Version: 0.1.0
Summary: A Python wrapper for yq exposing the toml functionality
Home-page: https://github.com/cmeister2/tomlq
Author: Max Dymond
Author-email: cmeister2@gmail.com
License: MIT license
Keywords: tomlq
Platform: UNKNOWN
Classifier: Development Status :: 2 - Pre-Alpha
Classifier: Intended Audience :: Developers
Classifier: License :: OSI Approved :: MIT License
Classifier: Natural Language :: English
Classifier: Programming Language :: Python :: 2
Classifier: Programming Language :: Python :: 2.7
Classifier: Programming Language :: Python :: 3
Classifier: Programming Language :: Python :: 3.4
Classifier: Programming Language :: Python :: 3.5
Classifier: Programming Language :: Python :: 3.6
Classifier: Programming Language :: Python :: 3.7
Requires-Dist: yq[toml] (>=2.7.2)
